odoo/addons/ssi_git/README.rst
odoo/addons/ssi_git/__init__.py
odoo/addons/ssi_git/__manifest__.py
odoo/addons/ssi_git/menu.xml
odoo/addons/ssi_git/models/__init__.py
odoo/addons/ssi_git/models/git_branch.py
odoo/addons/ssi_git/models/git_repo.py
odoo/addons/ssi_git/models/git_repo_type.py
odoo/addons/ssi_git/models/res_company.py
odoo/addons/ssi_git/models/res_config_settings.py
odoo/addons/ssi_git/security/ir.model.access.csv
odoo/addons/ssi_git/security/ir_module_category_data.xml
odoo/addons/ssi_git/security/res_group_data.xml
odoo/addons/ssi_git/static/description/icon.png
odoo/addons/ssi_git/views/git_branch_views.xml
odoo/addons/ssi_git/views/git_repo_type_views.xml
odoo/addons/ssi_git/views/git_repo_views.xml
odoo/addons/ssi_git/views/res_config_settings_views.xml
odoo14_addon_ssi_git-14.0.2.1.0.dist-info/METADATA
odoo14_addon_ssi_git-14.0.2.1.0.dist-info/WHEEL
odoo14_addon_ssi_git-14.0.2.1.0.dist-info/top_level.txt
odoo14_addon_ssi_git-14.0.2.1.0.dist-info/RECORD
